collegra/__init__.py
collegra/cli.py
collegra/collegra.py
collegra-0.1.0.dist-info/WHEEL
collegra-0.1.0.dist-info/METADATA
collegra-0.1.0.dist-info/RECORD
